Metadata-Version: 2.1
Name: lastfmtagupdater
Version: 3.1.0
Summary: Update your music files with tags from Last.FM
Author: Brent Huisman
Author-email: brent@huisman.pl
Maintainer-email: Brent Huisman <brent@huisman.pl>
License:                     GNU GENERAL PUBLIC LICENSE
Project-URL: homepage, https://github.com/brenthuisman/lastfmtagupdater
Project-URL: documentation, https://github.com/brenthuisman/lastfmtagupdater
Project-URL: repository, https://github.com/brenthuisman/lastfmtagupdater
Project-URL: changelog, https://github.com/brenthuisman/lastfmtagupdater/blob/master/README.md
Keywords: lastfm,music,tag,update
Classifier: Development Status :: 5 - Production/Stable
Classifier: License :: OSI Approved :: GNU General Public License v3 (GPLv3)
Classifier: Programming Language :: Python :: 3
Classifier: Environment :: Console
Classifier: Topic :: Utilities
Classifier: Topic :: Multimedia :: Sound/Audio
Classifier: Operating System :: OS Independent
Requires-Python: >=3.6
License-File: LICENSE.txt
